<annotation>
	<folder>images</folder>
	<filename>22.jpg</filename>
	<path>D:\file\皱纹\images\images\22.jpg</path>
	<source>
		<database>Unknown</database>
	</source>
	<size>
		<width>2448</width>
		<height>3264</height>
		<depth>3</depth>
	</size>
	<segmented>0</segmented>
	<object>
		<name>Nasal pattern</name>
		<pose>Unspecified</pose>
		<truncated>0</truncated>
		<difficult>0</difficult>
		<bndbox>
			<xmin>1300</xmin>
			<ymin>2222</ymin>
			<xmax>1588</xmax>
			<ymax>2620</ymax>
		</bndbox>
	</object>
	<object>
		<name>Nasal pattern</name>
		<pose>Unspecified</pose>
		<truncated>0</truncated>
		<difficult>0</difficult>
		<bndbox>
			<xmin>563</xmin>
			<ymin>2251</ymin>
			<xmax>788</xmax>
			<ymax>2615</ymax>
		</bndbox>
	</object>
</annotation>
